Metadata-Version: 2.4
Name: dioptra-zeph
Version: 1.3.5
Summary: An orchestrator for distributed IP tracing
License: MIT
License-File: LICENSE
Author: Matthieu Gouel
Author-email: matthieu.gouel@protonmail.com
Requires-Python: >=3.10,<4.0
Classifier: License :: OSI Approved :: MIT License
Classifier: Programming Language :: Python :: 3
Classifier: Programming Language :: Python :: 3.10
Classifier: Programming Language :: Python :: 3.11
Classifier: Programming Language :: Python :: 3.12
Classifier: Programming Language :: Python :: 3.13
Classifier: Programming Language :: Python :: 3.14
Requires-Dist: diamond-miner (>=1.1.3,<2.0.0)
Requires-Dist: dioptra-iris-client (>=0.5.2,<0.6.0)
Requires-Dist: py-radix (>=0.10.0,<0.11.0)
Requires-Dist: pyasn (>=1.6.2,<2.0.0)
Requires-Dist: pych-client[orjson] (>=0.4.1,<0.5.0)
Requires-Dist: requests (>=2.31.0,<3.0.0)
Requires-Dist: tqdm (>=4.66.1,<5.0.0)
Requires-Dist: typer (>=0.16.1,<0.17.0)
Requires-Dist: wheel (>=0.45.1,<0.46.0)
Project-URL: Homepage, https://github.com/dioptra-io/zeph
